{
  "captured_at": "2026-06-02T17:37:20.859928+00:00",
  "backend": "ibm_marrakesh",
  "job_id": "d8fh8u1vjngc73apt16g",
  "shots": 4096,
  "mitigation": "off",
  "metrics": {
    "caller": "qiskit_ibm_runtime~sampler.py",
    "qiskit_version": "qiskit_ibm_runtime-0.47.0,qiskit-2.4.1*,qiskit_aer-0.17.2*",
    "timestamps": {
      "created": "2026-06-02T17:35:52.417931Z",
      "finished": "2026-06-02T17:37:19.566883Z",
      "running": "2026-06-02T17:35:53.555648Z"
    },
    "bss": {
      "seconds": 72
    },
    "usage": {
      "quantum_seconds": 72,
      "seconds": 72,
      "status": "complete"
    }
  },
  "per_n_mean": {
    "8": 0.80185546875,
    "16": 0.47806396484375,
    "32": 0.03563232421875
  },
  "random_floor": {
    "8": 0.125,
    "16": 0.0625,
    "32": 0.03125
  },
  "records": [
    {
      "n": 3,
      "marked": "000",
      "rep": 0,
      "p_marked": 0.82080078125
    },
    {
      "n": 3,
      "marked": "000",
      "rep": 1,
      "p_marked": 0.806396484375
    },
    {
      "n": 3,
      "marked": "000",
      "rep": 2,
      "p_marked": 0.8134765625
    },
    {
      "n": 3,
      "marked": "000",
      "rep": 3,
      "p_marked": 0.815673828125
    },
    {
      "n": 3,
      "marked": "000",
      "rep": 4,
      "p_marked": 0.79443359375
    },
    {
      "n": 3,
      "marked": "010",
      "rep": 0,
      "p_marked": 0.801513671875
    },
    {
      "n": 3,
      "marked": "010",
      "rep": 1,
      "p_marked": 0.810546875
    },
    {
      "n": 3,
      "marked": "010",
      "rep": 2,
      "p_marked": 0.8095703125
    },
    {
      "n": 3,
      "marked": "010",
      "rep": 3,
      "p_marked": 0.810302734375
    },
    {
      "n": 3,
      "marked": "010",
      "rep": 4,
      "p_marked": 0.8076171875
    },
    {
      "n": 3,
      "marked": "101",
      "rep": 0,
      "p_marked": 0.780517578125
    },
    {
      "n": 3,
      "marked": "101",
      "rep": 1,
      "p_marked": 0.819580078125
    },
    {
      "n": 3,
      "marked": "101",
      "rep": 2,
      "p_marked": 0.82373046875
    },
    {
      "n": 3,
      "marked": "101",
      "rep": 3,
      "p_marked": 0.77490234375
    },
    {
      "n": 3,
      "marked": "101",
      "rep": 4,
      "p_marked": 0.782470703125
    },
    {
      "n": 3,
      "marked": "111",
      "rep": 0,
      "p_marked": 0.78857421875
    },
    {
      "n": 3,
      "marked": "111",
      "rep": 1,
      "p_marked": 0.79931640625
    },
    {
      "n": 3,
      "marked": "111",
      "rep": 2,
      "p_marked": 0.799560546875
    },
    {
      "n": 3,
      "marked": "111",
      "rep": 3,
      "p_marked": 0.79296875
    },
    {
      "n": 3,
      "marked": "111",
      "rep": 4,
      "p_marked": 0.78515625
    },
    {
      "n": 4,
      "marked": "0000",
      "rep": 0,
      "p_marked": 0.482421875
    },
    {
      "n": 4,
      "marked": "0000",
      "rep": 1,
      "p_marked": 0.486572265625
    },
    {
      "n": 4,
      "marked": "0000",
      "rep": 2,
      "p_marked": 0.486083984375
    },
    {
      "n": 4,
      "marked": "0000",
      "rep": 3,
      "p_marked": 0.49609375
    },
    {
      "n": 4,
      "marked": "0000",
      "rep": 4,
      "p_marked": 0.4990234375
    },
    {
      "n": 4,
      "marked": "0101",
      "rep": 0,
      "p_marked": 0.466064453125
    },
    {
      "n": 4,
      "marked": "0101",
      "rep": 1,
      "p_marked": 0.46875
    },
    {
      "n": 4,
      "marked": "0101",
      "rep": 2,
      "p_marked": 0.4755859375
    },
    {
      "n": 4,
      "marked": "0101",
      "rep": 3,
      "p_marked": 0.48388671875
    },
    {
      "n": 4,
      "marked": "0101",
      "rep": 4,
      "p_marked": 0.471435546875
    },
    {
      "n": 4,
      "marked": "1010",
      "rep": 0,
      "p_marked": 0.465087890625
    },
    {
      "n": 4,
      "marked": "1010",
      "rep": 1,
      "p_marked": 0.4736328125
    },
    {
      "n": 4,
      "marked": "1010",
      "rep": 2,
      "p_marked": 0.4609375
    },
    {
      "n": 4,
      "marked": "1010",
      "rep": 3,
      "p_marked": 0.495849609375
    },
    {
      "n": 4,
      "marked": "1010",
      "rep": 4,
      "p_marked": 0.477294921875
    },
    {
      "n": 4,
      "marked": "1111",
      "rep": 0,
      "p_marked": 0.45654296875
    },
    {
      "n": 4,
      "marked": "1111",
      "rep": 1,
      "p_marked": 0.4892578125
    },
    {
      "n": 4,
      "marked": "1111",
      "rep": 2,
      "p_marked": 0.474609375
    },
    {
      "n": 4,
      "marked": "1111",
      "rep": 3,
      "p_marked": 0.479736328125
    },
    {
      "n": 4,
      "marked": "1111",
      "rep": 4,
      "p_marked": 0.472412109375
    },
    {
      "n": 5,
      "marked": "00000",
      "rep": 0,
      "p_marked": 0.03369140625
    },
    {
      "n": 5,
      "marked": "00000",
      "rep": 1,
      "p_marked": 0.036865234375
    },
    {
      "n": 5,
      "marked": "00000",
      "rep": 2,
      "p_marked": 0.035888671875
    },
    {
      "n": 5,
      "marked": "00000",
      "rep": 3,
      "p_marked": 0.041015625
    },
    {
      "n": 5,
      "marked": "00000",
      "rep": 4,
      "p_marked": 0.037353515625
    },
    {
      "n": 5,
      "marked": "01010",
      "rep": 0,
      "p_marked": 0.037353515625
    },
    {
      "n": 5,
      "marked": "01010",
      "rep": 1,
      "p_marked": 0.0361328125
    },
    {
      "n": 5,
      "marked": "01010",
      "rep": 2,
      "p_marked": 0.031982421875
    },
    {
      "n": 5,
      "marked": "01010",
      "rep": 3,
      "p_marked": 0.034912109375
    },
    {
      "n": 5,
      "marked": "01010",
      "rep": 4,
      "p_marked": 0.035888671875
    },
    {
      "n": 5,
      "marked": "10101",
      "rep": 0,
      "p_marked": 0.035400390625
    },
    {
      "n": 5,
      "marked": "10101",
      "rep": 1,
      "p_marked": 0.033203125
    },
    {
      "n": 5,
      "marked": "10101",
      "rep": 2,
      "p_marked": 0.03125
    },
    {
      "n": 5,
      "marked": "10101",
      "rep": 3,
      "p_marked": 0.03271484375
    },
    {
      "n": 5,
      "marked": "10101",
      "rep": 4,
      "p_marked": 0.036865234375
    },
    {
      "n": 5,
      "marked": "11111",
      "rep": 0,
      "p_marked": 0.03759765625
    },
    {
      "n": 5,
      "marked": "11111",
      "rep": 1,
      "p_marked": 0.037353515625
    },
    {
      "n": 5,
      "marked": "11111",
      "rep": 2,
      "p_marked": 0.028564453125
    },
    {
      "n": 5,
      "marked": "11111",
      "rep": 3,
      "p_marked": 0.037353515625
    },
    {
      "n": 5,
      "marked": "11111",
      "rep": 4,
      "p_marked": 0.041259765625
    }
  ]
}