{
  "demo": "01-branch-prediction",
  "title": "Sorted vs unsorted branch prediction",
  "machine": {
    "cpu": "AMD Ryzen 7 3800X 8-Core Processor",
    "cores_physical": 8,
    "cores_logical": 8,
    "smt_enabled": false,
    "ram_gb": 31,
    "ram_speed_mhz": null,
    "compiler": "gcc (Ubuntu 13.3.0-6ubuntu2~24.04.1) 13.3.0",
    "kernel": "6.8.0-111-generic",
    "governor": "performance",
    "turbo": null,
    "isolated_cpus": "0-7",
    "cpu_affinity": "4-7"
  },
  "captured_at": "2026-05-17T07:13:50Z",
  "runs": [
    {
      "variant": "sorted",
      "n": 1024,
      "iterations": 34733,
      "ns_per_op": {
        "median": 20344.2846,
        "min": 20193.841,
        "p99": 20373.0394,
        "iqr": 41.4717
      },
      "ops_per_sec": 50336323,
      "branch_misses_per_op": 0.0088,
      "instructions_per_cycle": 2.877
    },
    {
      "variant": "sorted",
      "n": 10240,
      "iterations": 27867,
      "ns_per_op": {
        "median": 25092.3741,
        "min": 25055.0899,
        "p99": 25143.4802,
        "iqr": 31.6137
      },
      "ops_per_sec": 408099362,
      "branch_misses_per_op": 0.0009,
      "instructions_per_cycle": 3.206
    },
    {
      "variant": "sorted",
      "n": 102400,
      "iterations": 9741,
      "ns_per_op": {
        "median": 72442.2791,
        "min": 72318.6008,
        "p99": 72758.9117,
        "iqr": 245.2064
      },
      "ops_per_sec": 1414009799,
      "branch_misses_per_op": 0.0001,
      "instructions_per_cycle": 3.286
    },
    {
      "variant": "sorted",
      "n": 1048576,
      "iterations": 1268,
      "ns_per_op": {
        "median": 555554.7244,
        "min": 547866.817,
        "p99": 557995.9388,
        "iqr": 5763.4172
      },
      "ops_per_sec": 1888381372,
      "branch_misses_per_op": 0.0,
      "instructions_per_cycle": 3.275
    },
    {
      "variant": "sorted",
      "n": 10485760,
      "iterations": 117,
      "ns_per_op": {
        "median": 5849846.7009,
        "min": 5590484.5897,
        "p99": 6110469.7975,
        "iqr": 76714.1923
      },
      "ops_per_sec": 1792787494,
      "branch_misses_per_op": 0.0,
      "instructions_per_cycle": 3.009
    },
    {
      "variant": "sorted",
      "n": 33554432,
      "iterations": 38,
      "ns_per_op": {
        "median": 18516851.0263,
        "min": 18036460.5789,
        "p99": 19437862.4792,
        "iqr": 267241.5132
      },
      "ops_per_sec": 1812142051,
      "branch_misses_per_op": 0.0,
      "instructions_per_cycle": 3.028
    },
    {
      "variant": "unsorted",
      "n": 1024,
      "iterations": 32859,
      "ns_per_op": {
        "median": 21205.1856,
        "min": 21162.6763,
        "p99": 21263.3394,
        "iqr": 30.6094
      },
      "ops_per_sec": 48292411,
      "branch_misses_per_op": 0.0107,
      "instructions_per_cycle": 1.699
    },
    {
      "variant": "unsorted",
      "n": 10240,
      "iterations": 14743,
      "ns_per_op": {
        "median": 47235.1447,
        "min": 47044.9645,
        "p99": 47491.2459,
        "iqr": 77.978
      },
      "ops_per_sec": 216809674,
      "branch_misses_per_op": 0.3016,
      "instructions_per_cycle": 0.64
    },
    {
      "variant": "unsorted",
      "n": 102400,
      "iterations": 1720,
      "ns_per_op": {
        "median": 403886.4613,
        "min": 402801.9128,
        "p99": 406738.4636,
        "iqr": 2681.0913
      },
      "ops_per_sec": 253663753,
      "branch_misses_per_op": 0.4974,
      "instructions_per_cycle": 0.446
    },
    {
      "variant": "unsorted",
      "n": 1048576,
      "iterations": 178,
      "ns_per_op": {
        "median": 3889763.691,
        "min": 3880712.3258,
        "p99": 3949279.1154,
        "iqr": 10472.3624
      },
      "ops_per_sec": 269589245,
      "branch_misses_per_op": 0.5004,
      "instructions_per_cycle": 0.452
    },
    {
      "variant": "unsorted",
      "n": 10485760,
      "iterations": 18,
      "ns_per_op": {
        "median": 39323508.6667,
        "min": 39102628.5,
        "p99": 39568657.0567,
        "iqr": 238946.5694
      },
      "ops_per_sec": 266684628,
      "branch_misses_per_op": 0.5,
      "instructions_per_cycle": 0.445
    },
    {
      "variant": "unsorted",
      "n": 33554432,
      "iterations": 6,
      "ns_per_op": {
        "median": 125265020.25,
        "min": 123999398.5,
        "p99": 126555510.3183,
        "iqr": 1044889.9583
      },
      "ops_per_sec": 267881234,
      "branch_misses_per_op": 0.5001,
      "instructions_per_cycle": 0.447
    }
  ],
  "notes": "Branch predictor learns sorted patterns; unsorted forces ~50% mispredicts."
}